{"name":"Chinaapi","tagline":"集成国内一些主流的API","body":"ChinaAPI\r\n=========================\r\n\r\nChinaAPI是一个API库，使用Python编写。\r\n\r\n目前国内的几大开放平台，有新浪微博，腾讯微博，淘宝等。\r\n针对这几个平台，用Python语言编写的API库都比较独立，各具特色。\r\n但仔细分析，不难发现这些库存在大量可通用的模块，并可抽象出统一的调用接口。\r\nChinaAPI就是为此目的而存在。\r\n\r\n安装\r\n----\r\n\r\n安装 ChinaAPI，最简单的方法:\r\n\r\n.. code-block:: bash\r\n\r\n    $ pip install chinaapi\r\n\r\n注：ChinaAPI所使用HTTP模块是Requests: https://github.com/kennethreitz/requests\r\n\r\n----\r\n\r\n新浪微博API:\r\n------------\r\n\r\n使用方法：\r\n\r\n.. code-block:: python\r\n\r\n        from chinaapi.sina_weibo import ApiClient\r\n        from chinaapi.utils.models import App, Token\r\n\r\n\r\n        # client的设置\r\n        app = App('app_key', 'app_secret')  # 填上自己的app_key，app_secret\r\n        token = Token('access_token')  # 填上取得的access_token\r\n        client = ApiClient(app)\r\n        client.set_access_token(token)\r\n\r\n        # 获取用户信息，对应的接口是：users/show\r\n        r = client.users.show(uid=1904178193)\r\n        print r.name  # 显示用户昵称：微博开放平台\r\n\r\n        # 发布带图片的微博，对应的接口是：statuses/upload\r\n        pic = open('pic.jpg', 'rb')\r\n        r = client.statuses.upload(status=u'发布的内容', pic=pic)\r\n        print r.id  # 显示发布成功的微博的编号（即mid）：1234567890123456\r\n\r\n\r\n调用规则：**斜杠（/）映射为点（.）**\r\n\r\n- users/show    ==>    client.users.show()\r\n- statuses/upload     ==>    client.statuses.upload()\r\n\r\n----\r\n\r\n淘宝API:\r\n------------\r\n\r\n\r\n使用示例：\r\n\r\n.. code-block:: python\r\n\r\n        from chinaapi.taobao import ApiClient\r\n        from chinaapi.utils.models import App\r\n\r\n\r\n        # client的设置\r\n        app = App('app_key', 'app_secret')  # 填上自己的app_key，app_secret\r\n        client = ApiClient(app)\r\n\r\n        # 获取淘宝客店铺列表，对应的接口是：taobao.tbk.shops.get\r\n        r = self.client.tbk.shops.get(cid=14, fields='user_id,seller_nick,shop_title,pic_url')\r\n        print len(r.tbk_shops_get_response.tbk_shops.tbk_shop)  # 显示店铺列表的数量：40\r\n\r\n\r\n调用规则：**直接映射（可省略前缀taobao.）**\r\n\r\n- taobao.itemcats.get    ==>    client.itemcats.get()  或者  client.taobao.itemcats.get()\r\n- taobao.tbk.shops.get   ==>    client.tbk.shops.get()  或者  client.taobao.tbk.shops.get()\r\n\r\n----\r\n\r\nTODO：\r\n-----------------------------------\r\n\r\n- 整合腾讯微博API\r\n- 整合各平台API的OAuth2调用模块\r\n\r\n感谢以下Python SDK的开发者们的贡献：\r\n-----------------------------------\r\n\r\n- 新浪微博：https://github.com/michaelliao/sinaweibopy\r\n- 腾讯微博：https://github.com/upbit/tweibo-pysdk\r\n- 淘宝：https://github.com/sempr/taobaopy","google":"","note":"Don't delete this file! It's used internally to help with page regeneration."}